pycalc_permission/__init__.py
pycalc_permission/authentication.py
pycalc_permission/permission.py
pycalc_permission/token.py
pycalc_permission/user.py
pycalc_permission-0.0.3.dist-info/LICENSE
pycalc_permission-0.0.3.dist-info/METADATA
pycalc_permission-0.0.3.dist-info/WHEEL
pycalc_permission-0.0.3.dist-info/top_level.txt
pycalc_permission-0.0.3.dist-info/RECORD
