Metadata-Version: 2.1
Name: pycalc_permission
Version: 0.0.3
Summary: A PyCalc permission package
Author-email: AE <AlekseevE2015@yandex.ru>
Classifier: Programming Language :: Python :: 3
Classifier: License :: OSI Approved :: MIT License
Classifier: Operating System :: OS Independent
Requires-Python: >=3.8
License-File: LICENSE
